MonitorLog/Demo.py
MonitorLog/__init__.py
MonitorLog-1.0.0.dist-info/LICENSE
MonitorLog-1.0.0.dist-info/METADATA
MonitorLog-1.0.0.dist-info/WHEEL
MonitorLog-1.0.0.dist-info/top_level.txt
MonitorLog-1.0.0.dist-info/RECORD
