Metadata-Version: 2.1
Name: MonitorLog
Version: 1.0.0
Summary: Python 监控日志!
Home-page: https://github.com/EVA-JianJun/MonitorLog
Author: jianjun
Author-email: 910667956@qq.com
License: UNKNOWN
Platform: UNKNOWN
Requires-Dist: psutil
Requires-Dist: portalocker
Requires-Dist: Pyinstaller
